ASBPredictor/__init__.py
ASBPredictor/model.pkl
ASBPredictor/predictor.py
ASBPredictor-0.1.1.dist-info/METADATA
ASBPredictor-0.1.1.dist-info/WHEEL
ASBPredictor-0.1.1.dist-info/entry_points.txt
ASBPredictor-0.1.1.dist-info/top_level.txt
ASBPredictor-0.1.1.dist-info/RECORD
