Metadata-Version: 2.1
Name: ASBPredictor
Version: 0.1.1
Summary: A Python package for predicting ASB risk from clinical data.
Home-page: https://github.com/yangfangs/ASBPredictor
Author: Yang Fang
Author-email: yangfangscu@gmail.com
Classifier: Programming Language :: Python :: 3
Classifier: License :: OSI Approved :: MIT License
Classifier: Operating System :: OS Independent
Requires-Python: >=3.6
Requires-Dist: pandas>=1.0.0
Requires-Dist: scikit-learn>=1.5.0
